{ 
    "resumeVersions":
        {
            "1":{ 
                "userID": "1",
                "name": "V1", 
                "language":"English", 
                "templateID": 1,					
                "personalInfo":{		
                    "title": "Personal Details",
                    "icon":"ion-android-contact",																				
                    "name":  "Metwalli Mohsen",
                    "mobile" : "+967 771238988",		 	
                    "email" : "Metwalli0@gmail.com",
                    "dob" : "1982-05-21", 
                    "maritalstatus" : "Married", 		 
                    "nationality" : "Yemeni",
                    "address" : "16 St., Sana\"a, Yemen",		 
                    "profile" : "Manage Servers(HP and IBM), WIPRO Healthcare Information System (HIS) Administrator, Train all Users in the Hospital to work in the System,Solve any Issue in the System",
                    "image" : "2.jpg",
                    "socialList":
                    [               
                        {"icon": "ion-university", "label": "", "link": "link.com"}   
                    ]                  
                },						
                "sectionIDs":
                [
                    "1", "2", "3", "4", "5", "6", "7"
                ]                              
            },	
            "2":{
                "userID": "1",
                "name": "V2", 
                "language":"Arabic",
                "templateID": 1,
                "personalInfo":
                {
                    "title": "البيانات الشخصية",
                    "icon": ".ion-ios-heart",
                    "name":  "متولي عبدالودود",
                    "mobile" : "+967 771238988",		 	
                    "email" : "Metwalli0@gmail.com",
                    "dob" : "21/05/1982", 
                    "maritalstatus" : "متزوج", 		 
                    "nationality" : "يمني",
                    "address" : "ش 16، اليمن",		 
                    "profile" : "إدارة منتمنتنمتنمتيبيب",
                    "image" : "",
                    "socialList":
                    [               
                        {"icon": "ion-university", "label": "", "link": "link.com"}   
                    ]   
                },
                "sectionList":
                [
                    {                                
                        "versionID": "1",
                        "title": "Education", 
                        "icon":"ion-university",
                        "type":"education",
                        "itemList":
                        [
                            {
                                "degree": "Bachelor(BSc) Computer Science",
                                "institute":"Sanaa University",
                                "country": "Yemen1",					
                                "description": "TOEFL iBT reading  or topic. The excerpts are changed as ",	
                                "dateFrom":"2002-09-02",
                                "dateTo": "2006-07-30"
                            },
                            {
                                "degree": "Secondery School, Scientific section",
                                "institute":"Al-Kuwait Secondary School",
                                "country": "Yemen",
                                "description": "TOEFL ",				
                                "dateFrom":"1998-09-01",
                                "dateTo": "2001-07-30"
                            }
                        ]                                       
                    },							
                "2":{ 
                        "versionID": "1",
                        "title": "Certificate", 
                        "icon":"ion-ribbon-b", 
                        "type":"certificate",
                        "itemList": 
                        [
                            {
                                "name": "Implementation Experience",
                                "authority":"Huburge University Hospital",
                                "url": "www.g.com",					
                                "details": "TOEFL iBT reading passages are excerpts from college-level textbooks that would be used in introductions to a discipline or topic. The excerpts are changed as little as possible because the goal of the TOEFL iBT is to assess how well students",	
                                "issuDate":"2002-09-02"
                            },
                            {
                                "name": "Certificate 2",
                                "authority":"Sanaa University",
                                "url": "Yemen1",					
                                "details": "TOEFL iBT",
                                "issuDate":"2002-09-02"
                            }
                        ]
                    },
                "3":{ 
                        "versionID": "1",
                        "title": "Work Experience", 
                        "icon":"ion-briefcase", 
                        "type":"experience",
                        "itemList": 
                        [
                            {
                                "jobTitle": "IT Engineer",
                                "company":"Typical Police Hospital",
                                "country": "Yemen",					
                                "description": "TOEFL iBT reading passages are excerpts from college-level textbooks that would be used in introductions to a discipline or topic. The excerpts are changed as little as possible because the goal of the TOEFL iBT is to assess how well students",	
                                "dateFrom":"1998-09-01",
                                "dateTo": "2001-07-30"
                            },
                            {
                                "jobTitle": "IT Officer",
                                "company":"ESDR",
                                "country": "Yemen",					
                                "description": "TOEFL iBT reading passages are excerpts from college-level textbooks that would be used in introductions to a discipline or topic. The excerpts are changed as little as possible because the goal of the TOEFL iBT is to assess how well students",	
                                "dateFrom":"1998-09-01",
                                "dateTo": "2001-07-30"
                            }
                        ]
                    },
                "4":{ 
                        "versionID": "1",
                        "title": "Award", 
                        "icon":"ion-trophy", 
                        "type":"award",
                        "itemList": 
                        [
                            {
                                "title": "Implementation Experience",
                                "presentedBy":"Huburge University Hospital",
                                "url": "www.g.com",					
                                "details": "TOEFL iBT reading passages are excerpts from college-level textbooks that would be used in introductions to a discipline or topic. The excerpts are changed as little as possible because the goal of the TOEFL iBT is to assess how well students",	
                                "date":"2002-09-02"
                            },
                            {
                                "title": "abcd efgh ijklmn",
                                "presentedBy":"Sanaa University",
                                "url": "Yemen1",					
                                "details": "TOEFL iBT",
                                "date":"2002-09-02"
                            }
                        ]
                    },
                "5":{ 
                        "versionID": "1",
                        "title": "Languages", 
                        "icon":"ion-earth", 
                        "type":"language",
                        "itemList": 
                        [
                            {	"name": "Arabic", "level": 10 },
                            {	"name": "English", "level": 8 }
                        ]
                    },
                "6":{ 
                        "versionID": "1",
                        "title": "Hobbies", 
                        "icon":"ion-earth", 
                        "type":"hobby",
                        "itemList": 
                        [									
                            {	"name": "Hobby-1", "icon": "ion-android-bicycle" },
                            {	"name": "Hobby-2", "icon": "" }
                        ]
                    },
                "7":{ 
                        "versionID": "1",
                        "title": "Skills", 
                        "icon":"ion-android-star-half", 
                        "type":"skills",
                        "itemList": 
                        [
                            {	
                                "name": "Programming Languages",
                                "itemList":
                                [
                                    {"name": "Java", "level": 8},
                                    {"name": "C++", "level": 7},
                                    {"name": "PHP", "level": 5},
                                    {"name": "VB", "level": 2},
                                    {"name": "HTML", "level": 9},
                                    {"name": "JavaScript", "level": 6},
                                    {"name": "CSS", "level": 8}											
                                ]
                            },
                            {	
                                "name": "Application",
                                "itemList":
                                [
                                    {"name": "Microsoft Office", "level": 8},
                                    {"name": "Adobe Photoshop", "level": 5},
                                    {"name": "SPSS", "level": 3},
                                    {"name": "Exchange Server", "level": 9}																						
                                ]
                            }
                        ]
                    }
                ]                  
            }
    },   					                						
    "versionSections":
    {
        "1":{                                
                "versionID": "1",
                "title": "Education", 
                "icon":"ion-university",
                "type":"education",
                "itemList":
                [
                    {
                        "degree": "Bachelor(BSc) Computer Science",
                        "institute":"Sanaa University",
                        "country": "Yemen1",					
                        "description": "TOEFL iBT reading  or topic. The excerpts are changed as ",	
                        "dateFrom":"2002-09-02",
                        "dateTo": "2006-07-30"
                    },
                    {
                        "degree": "Secondery School, Scientific section",
                        "institute":"Al-Kuwait Secondary School",
                        "country": "Yemen",
                        "description": "TOEFL ",				
                        "dateFrom":"1998-09-01",
                        "dateTo": "2001-07-30"
                    }
                ]                                       
            },							
        "2":{ 
                "versionID": "1",
                "title": "Certificate", 
                "icon":"ion-ribbon-b", 
                "type":"certificate",
                "itemList": 
                [
                    {
                        "name": "Implementation Experience",
                        "authority":"Huburge University Hospital",
                        "url": "www.g.com",					
                        "details": "TOEFL iBT reading passages are excerpts from college-level textbooks that would be used in introductions to a discipline or topic. The excerpts are changed as little as possible because the goal of the TOEFL iBT is to assess how well students",	
                        "issuDate":"2002-09-02"
                    },
                    {
                        "name": "Certificate 2",
                        "authority":"Sanaa University",
                        "url": "Yemen1",					
                        "details": "TOEFL iBT",
                        "issuDate":"2002-09-02"
                    }
                ]
            },
        "3":{ 
                "versionID": "1",
                "title": "Work Experience", 
                "icon":"ion-briefcase", 
                "type":"experience",
                "itemList": 
                [
                    {
                        "jobTitle": "IT Engineer",
                        "company":"Typical Police Hospital",
                        "country": "Yemen",					
                        "description": "TOEFL iBT reading passages are excerpts from college-level textbooks that would be used in introductions to a discipline or topic. The excerpts are changed as little as possible because the goal of the TOEFL iBT is to assess how well students",	
                        "dateFrom":"1998-09-01",
                        "dateTo": "2001-07-30"
                    },
                    {
                        "jobTitle": "IT Officer",
                        "company":"ESDR",
                        "country": "Yemen",					
                        "description": "TOEFL iBT reading passages are excerpts from college-level textbooks that would be used in introductions to a discipline or topic. The excerpts are changed as little as possible because the goal of the TOEFL iBT is to assess how well students",	
                        "dateFrom":"1998-09-01",
                        "dateTo": "2001-07-30"
                    }
                ]
            },
        "4":{ 
                "versionID": "1",
                "title": "Award", 
                "icon":"ion-trophy", 
                "type":"award",
                "itemList": 
                [
                    {
                        "title": "Implementation Experience",
                        "presentedBy":"Huburge University Hospital",
                        "url": "www.g.com",					
                        "details": "TOEFL iBT reading passages are excerpts from college-level textbooks that would be used in introductions to a discipline or topic. The excerpts are changed as little as possible because the goal of the TOEFL iBT is to assess how well students",	
                        "date":"2002-09-02"
                    },
                    {
                        "title": "abcd efgh ijklmn",
                        "presentedBy":"Sanaa University",
                        "url": "Yemen1",					
                        "details": "TOEFL iBT",
                        "date":"2002-09-02"
                    }
                ]
            },
        "5":{ 
                "versionID": "1",
                "title": "Languages", 
                "icon":"ion-earth", 
                "type":"language",
                "itemList": 
                [
                    {	"name": "Arabic", "level": 10 },
                    {	"name": "English", "level": 8 }
                ]
            },
        "6":{ 
                "versionID": "1",
                "title": "Hobbies", 
                "icon":"ion-earth", 
                "type":"hobby",
                "itemList": 
                [									
                    {	"name": "Hobby-1", "icon": "ion-android-bicycle" },
                    {	"name": "Hobby-2", "icon": "" }
                ]
            },
        "7":{ 
                "versionID": "1",
                "title": "Skills", 
                "icon":"ion-android-star-half", 
                "type":"skills",
                "itemList": 
                [
                    {	
                        "name": "Programming Languages",
                        "itemList":
                        [
                            {"name": "Java", "level": 8},
                            {"name": "C++", "level": 7},
                            {"name": "PHP", "level": 5},
                            {"name": "VB", "level": 2},
                            {"name": "HTML", "level": 9},
                            {"name": "JavaScript", "level": 6},
                            {"name": "CSS", "level": 8}											
                        ]
                    },
                    {	
                        "name": "Application",
                        "itemList":
                        [
                            {"name": "Microsoft Office", "level": 8},
                            {"name": "Adobe Photoshop", "level": 5},
                            {"name": "SPSS", "level": 3},
                            {"name": "Exchange Server", "level": 9}																						
                        ]
                    }
                ]
            }  
    }              
}